memviz/__init__.py
memviz/cli.py
memviz/run_memviz.sh
memviz-1.2.3.dist-info/LICENSE
memviz-1.2.3.dist-info/METADATA
memviz-1.2.3.dist-info/WHEEL
memviz-1.2.3.dist-info/entry_points.txt
memviz-1.2.3.dist-info/top_level.txt
memviz-1.2.3.dist-info/RECORD
