Metadata-Version: 2.1
Name: memviz
Version: 1.2.3
Summary: Embedded Low-Level Memory Visualization for C++
License: MIT License
Project-URL: Homepage, https://la-10.github.io/MemViz/
Project-URL: Repository, https://github.com/LA-10/MemViz
Requires-Python: >=3.8
License-File: LICENSE
